Metadata-Version: 2.1
Name: odoo-addon-document_quick_access
Version: 18.0.1.0.0.2
Requires-Python: >=3.10
Requires-Dist: odoo-addon-barcode_action==18.0.*
Requires-Dist: odoo==18.0.*
Requires-Dist: pdf2image
Requires-Dist: pyzbar
Summary: Document quick access
Home-page: https://github.com/OCA/server-ux
License: AGPL-3
Author: Creu Blanca,Odoo Community Association (OCA)
Author-email: support@odoo-community.org
Classifier: Programming Language :: Python
Classifier: Framework :: Odoo
Classifier: Framework :: Odoo :: 18.0
Classifier: License :: OSI Approved :: GNU Affero General Public License v3
